[
  {
    "title": "电力安全生产监管典型执法案例（29—31）",
    "url": "http://www.nea.gov.cn/2024-09/23/c_1212399372.htm",
    "source": "国家能源局",
    "category": "national",
    "date": "2026-07-06",
    "scrapedAt": "2026-07-06 14:07:16"
  },
  {
    "title": "电力安全生产监管典型执法案例（26—28）",
    "url": "http://www.nea.gov.cn/2024-06/24/c_1212374834.htm",
    "source": "国家能源局",
    "category": "national",
    "date": "2026-07-06",
    "scrapedAt": "2026-07-06 14:07:16"
  },
  {
    "title": "国家发展改革委 国家能源局关于建立煤炭产能储备制度的实施意见",
    "url": "http://zfxxgk.nea.gov.cn/2024-04/02/c_1310770967.htm",
    "source": "国家能源局",
    "category": "national",
    "date": "2026-07-06",
    "scrapedAt": "2026-07-06 14:07:16"
  },
  {
    "title": "《电力市场计量结算基本规则》是否适用于不属于市场经营主体的国家电网进行阶梯电价和分时电价 “一户一表”住宅用户的用电计量与结算",
    "url": "https://www.nea.gov.cn/20260706/dc1d414b8cd244e7b469fd071462c2be/c.html",
    "source": "国家能源局",
    "category": "grid",
    "date": "2026-07-06",
    "scrapedAt": "2026-07-06 14:07:16"
  },
  {
    "title": "承装（修、试）电力设施许可证 资质范围是什么？是否具备电力安全工器具的检测资质？",
    "url": "https://www.nea.gov.cn/20260706/74f8d28af4f8483db690aeb74146cd74/c.html",
    "source": "国家能源局",
    "category": "national",
    "date": "2026-07-06",
    "scrapedAt": "2026-07-06 14:07:16"
  },
  {
    "title": "国家能源局举办2026年煤层气勘探开发高级研修班",
    "url": "https://www.nea.gov.cn/20260706/320d329d684a4bb9822bd9cffdc562d3/c.html",
    "source": "国家能源局",
    "category": "national",
    "date": "2026-07-06",
    "scrapedAt": "2026-07-06 14:07:16"
  },
  {
    "title": "一带一路能源合作",
    "url": "https://obor.nea.gov.cn/",
    "source": "国家能源局",
    "category": "national",
    "date": "2026-07-06",
    "scrapedAt": "2026-07-06 14:07:16"
  },
  {
    "title": "能源行业标准化",
    "url": "https://114.251.111.103:18080/portal",
    "source": "国家能源局",
    "category": "national",
    "date": "2026-07-06",
    "scrapedAt": "2026-07-06 14:07:16"
  },
  {
    "title": "电力市场化交易专项整治反映问题渠道",
    "url": "https://www.nea.gov.cn/fywtjd/dljg.html",
    "source": "国家能源局",
    "category": "national",
    "date": "2026-07-06",
    "scrapedAt": "2026-07-06 14:07:16"
  },
  {
    "title": "能源法律法规",
    "url": "https://www.nea.gov.cn/nyflfg/index.htm",
    "source": "国家能源局",
    "category": "national",
    "date": "2026-07-06",
    "scrapedAt": "2026-07-06 14:07:16"
  },
  {
    "title": "可再生能源发电项目信息管理系统",
    "url": "https://sso.renewable.org.cn",
    "source": "国家能源局",
    "category": "national",
    "date": "2026-07-06",
    "scrapedAt": "2026-07-06 14:07:16"
  },
  {
    "title": "电力业务资质许可在线办理",
    "url": "https://zzxy.nea.gov.cn/",
    "source": "国家能源局",
    "category": "national",
    "date": "2026-07-06",
    "scrapedAt": "2026-07-06 14:07:16"
  },
  {
    "title": "能源监管信息平台",
    "url": "https://jianguan.renewable.org.cn/",
    "source": "国家能源局",
    "category": "national",
    "date": "2026-07-06",
    "scrapedAt": "2026-07-06 14:07:16"
  },
  {
    "title": "华北能源监管局",
    "url": "http://hbj.nea.gov.cn",
    "source": "国家能源局",
    "category": "national",
    "date": "2026-07-06",
    "scrapedAt": "2026-07-06 14:07:16"
  },
  {
    "title": "东北能源监管局",
    "url": "http://dbj.nea.gov.cn",
    "source": "国家能源局",
    "category": "national",
    "date": "2026-07-06",
    "scrapedAt": "2026-07-06 14:07:16"
  }
]
